gr_envs/__init__.py
gr_envs/_version.py
gr_envs/register.py
gr_envs/custom_env_wrappers/__init__.py
gr_envs/custom_env_wrappers/flat_obs_wrapper.py
gr_envs/env_registration/highway_register.py
gr_envs/env_registration/maze_register.py
gr_envs/env_registration/panda_register.py
gr_envs/highway_scripts/__init__.py
gr_envs/highway_scripts/envs/__init__.py
gr_envs/maze_scripts/__init__.py
gr_envs/maze_scripts/envs/__init__.py
gr_envs/minigrid_scripts/__init__.py
gr_envs/minigrid_scripts/envs/__init__.py
gr_envs/minigrid_scripts/envs/custom_color.py
gr_envs/minigrid_scripts/envs/dynamic_four_rooms.py
gr_envs/minigrid_scripts/envs/dynamic_goal_crossing.py
gr_envs/minigrid_scripts/envs/dynamic_goal_crossing_custom.py
gr_envs/minigrid_scripts/envs/dynamic_goal_empty.py
gr_envs/panda_scripts/__init__.py
gr_envs/panda_scripts/envs/__init__.py
gr_envs/wrappers/__init__.py
gr_envs/wrappers/goal_wrapper.py
gr_envs/wrappers/hook.py
gr_envs/wrappers/panda_wrapper.py
gr_envs/wrappers/parking_wrapper.py
gr_envs/wrappers/point_maze_wrapper.py
gr_envs-1.0.dist-info/licenses/LICENSE
gr_envs-1.0.dist-info/METADATA
gr_envs-1.0.dist-info/WHEEL
gr_envs-1.0.dist-info/top_level.txt
gr_envs-1.0.dist-info/RECORD
