Metadata-Version: 2.4
Name: gr_envs
Version: 1.0
Summary: Package to receive goal-directed environments
Author: Ben Nageris
Author-email: Matan Shamir <matan.shamir@live.biu.ac.il>, Osher Elhadad <osher.elhadad@live.biu.ac.il>
License-Expression: MIT
Classifier: Programming Language :: Python :: 3
Classifier: Operating System :: OS Independent
Requires-Python: >=3.11
License-File: LICENSE
Requires-Dist: gymnasium
Provides-Extra: minigrid
Requires-Dist: minigrid; extra == "minigrid"
Provides-Extra: highway
Requires-Dist: highway-env; extra == "highway"
Provides-Extra: maze
Requires-Dist: gymnasium-robotics; extra == "maze"
Provides-Extra: panda
Requires-Dist: panda_gym; extra == "panda"
Dynamic: license-file
